philter_lite/__init__.py
philter_lite/asterisk.py
philter_lite/configs/philter_delta.toml
philter_lite/coordinate_map.py
philter_lite/data/i2b2_anno/110-01.txt
philter_lite/data/i2b2_anno/110-02.txt
philter_lite/data/i2b2_anno/110-03.txt
philter_lite/data/i2b2_anno/110-04.txt
philter_lite/data/i2b2_anno/111-01.txt
philter_lite/data/i2b2_notes/110-01.txt
philter_lite/data/i2b2_notes/110-02.txt
philter_lite/data/i2b2_notes/110-03.txt
philter_lite/data/i2b2_notes/110-04.txt
philter_lite/data/i2b2_notes/111-01.txt
philter_lite/data/i2b2_xml/110-01.xml
philter_lite/data/i2b2_xml/110-02.xml
philter_lite/data/i2b2_xml/110-03.xml
philter_lite/data/i2b2_xml/110-04.xml
philter_lite/data/i2b2_xml/111-01.xml
philter_lite/data/phi/fn.txt
philter_lite/data/phi/fn_tags.txt
philter_lite/data/phi/fn_tags_context.txt
philter_lite/data/phi/fp.txt
philter_lite/data/phi/fp_tags.txt
philter_lite/data/phi/fp_tags_context.txt
philter_lite/data/phi/summary.json
philter_lite/data/phi_notes_i2b2.json
philter_lite/filters/__init__.py
philter_lite/filters/filter_db.py
philter_lite/filters/regex.toml
philter_lite/filters/regex_context.toml
philter_lite/filters/set.toml
philter_lite/filters/stanford_ner.py
philter_lite/i2b2.py
philter_lite/main.py
philter_lite/philter.py
philter_lite/py.typed
philter_lite-0.5.1.dist-info/LICENSE
philter_lite-0.5.1.dist-info/METADATA
philter_lite-0.5.1.dist-info/WHEEL
philter_lite-0.5.1.dist-info/entry_points.txt
philter_lite-0.5.1.dist-info/RECORD
