Metadata-Version: 2.1
Name: philter-lite
Version: 0.5.1
Summary: Open-source PHI-filtering software. A fork of philter-ucsf.
License: BSD-3-Clause
Author: Beau Norgeot
Author-email: beaunorgeot@gmail.com
Requires-Python: >=3.9,<4.0
Classifier: License :: OSI Approved :: BSD License
Classifier: Operating System :: OS Independent
Classifier: Programming Language :: Python
Classifier: Programming Language :: Python :: 3
Classifier: Programming Language :: Python :: 3.9
Classifier: Programming Language :: Python :: 3.10
Classifier: Programming Language :: Python :: 3.11
Classifier: Programming Language :: Python :: 3.12
Classifier: Programming Language :: Python :: 3.13
Requires-Dist: chardet (>=5.2.0,<6.0.0)
Requires-Dist: nltk (>=3.9.1,<4.0.0)
Requires-Dist: tomli (>=2.1.0,<3.0.0) ; python_version < "3.11"
Requires-Dist: xmltodict (>=0.14.2,<0.15.0)
